odoo/addons/ssi_helpdesk_portal/README.rst
odoo/addons/ssi_helpdesk_portal/__init__.py
odoo/addons/ssi_helpdesk_portal/__manifest__.py
odoo/addons/ssi_helpdesk_portal/controller/__init__.py
odoo/addons/ssi_helpdesk_portal/controller/main.py
odoo/addons/ssi_helpdesk_portal/controller/portal.py
odoo/addons/ssi_helpdesk_portal/data/website_helpdesk.xml
odoo/addons/ssi_helpdesk_portal/models/__init__.py
odoo/addons/ssi_helpdesk_portal/models/helpdesk.py
odoo/addons/ssi_helpdesk_portal/models/website.py
odoo/addons/ssi_helpdesk_portal/static/description/icon.png
odoo/addons/ssi_helpdesk_portal/static/src/js/ssi_helpdesk_portal.menu.js
odoo/addons/ssi_helpdesk_portal/static/src/js/website_helpdesk_form_editor.js
odoo/addons/ssi_helpdesk_portal/views/assets.xml
odoo/addons/ssi_helpdesk_portal/views/helpdesk_portal_templates.xml
odoo/addons/ssi_helpdesk_portal/views/helpdesk_templates.xml
odoo14_addon_ssi_helpdesk_portal-14.0.1.0.2.dist-info/METADATA
odoo14_addon_ssi_helpdesk_portal-14.0.1.0.2.dist-info/WHEEL
odoo14_addon_ssi_helpdesk_portal-14.0.1.0.2.dist-info/top_level.txt
odoo14_addon_ssi_helpdesk_portal-14.0.1.0.2.dist-info/RECORD
